[
    {
        "id": 1,
        "zone_id": 1,
        "name": "Lô biệt thự A1",
        "size": 300.0,
        "price": 5000000000,
        "deposit": 1000000000,
        "specific_address": "Khu biệt thự A, Phân khu Biệt Thự Vườn",
        "status": "empty",
        "description": "Lô đất biệt thự góc có tầm nhìn ra công viên.",
        "main_image" : "/customer/images/listing-1.jpg",
        "sub_image_1" : "/customer/images/image_1.jpg",
        "sub_image_2" : "/customer/images/image_2.jpg",
        "sub_image_3" : "/customer/images/image_3.jpg"
    },
    {
        "id": 2,
        "zone_id": 1,
        "name": "Lô biệt thự A2",
        "size": 280.0,
        "price": 4500000000,
        "deposit": 900000000,
        "specific_address": "Khu biệt thự A, Phân khu Biệt Thự Vườn",
        "status": "empty",
        "description": "Lô đất biệt thự nằm gần khu tiện ích chung.",
        "main_image" : "/customer/images/listing-2.jpg",
        "sub_image_1" : "/customer/images/image_3.jpg",
        "sub_image_2" : "/customer/images/image_4.jpg",
        "sub_image_3" : "/customer/images/image_5.jpg"
    },
    {
        "id": 3,
        "zone_id": 1,
        "name": "Lô biệt thự B1",
        "size": 320.0,
        "price": 5200000000,
        "deposit": 1100000000,
        "specific_address": "Khu biệt thự B, Phân khu Biệt Thự Vườn",
        "status": "empty",
        "description": "Lô đất biệt thự nằm cạnh đường lớn, tiện lợi giao thông.",
        "main_image" : "/customer/images/listing-3.jpg",
        "sub_image_1" : "/customer/images/image_4.jpg",
        "sub_image_2" : "/customer/images/image_5.jpg",
        "sub_image_3" : "/customer/images/image_6.jpg"
    },
    {
        "id": 4,
        "zone_id": 1,
        "name": "Lô biệt thự B2",
        "size": 300.0,
        "price": 4800000000,
        "deposit": 950000000,
        "specific_address": "Khu biệt thự B, Phân khu Biệt Thự Vườn",
        "status": "empty",
        "description": "Lô đất biệt thự gần hồ nước, không gian thoáng mát.",
        "main_image" : "/customer/images/listing-2.jpg",
        "sub_image_1" : "/customer/images/image_4.jpg",
        "sub_image_2" : "/customer/images/image_7.jpg",
        "sub_image_3" : "/customer/images/image_8.jpg"
    },
    {
        "id": 5,
        "zone_id": 1,
        "name": "Lô biệt thự C1",
        "size": 310.0,
        "price": 4900000000,
        "deposit": 1000000000,
        "specific_address": "Khu biệt thự C, Phân khu Biệt Thự Vườn",
        "status": "empty",
        "description": "Lô đất biệt thự góc 2 mặt tiền, gần khu vực yên tĩnh.",
        "main_image" : "/customer/images/listing-4.jpg",
        "sub_image_1" : "/customer/images/image_6.jpg",
        "sub_image_2" : "/customer/images/image_7.jpg",
        "sub_image_3" : "/customer/images/image_8.jpg"
    },
    {
        "id": 6,
        "zone_id": 2,
        "name": "Lô căn hộ A1",
        "size": 80.0,
        "price": 1200000000,
        "deposit": 300000000,
        "specific_address": "Tầng 1, Tòa nhà A, Phân khu Căn Hộ Cao Cấp",
        "status": "empty",
        "description": "Căn hộ 2 phòng ngủ, gần khu trung tâm thương mại.",
        "main_image" : "/customer/images/listing-5.jpg",
        "sub_image_1" : "/customer/images/image_6.jpg",
        "sub_image_2" : "/customer/images/image_3.jpg",
        "sub_image_3" : "/customer/images/image_2.jpg"
    },
    {
        "id": 7,
        "zone_id": 2,
        "name": "Lô căn hộ A2",
        "size": 75.0,
        "price": 1100000000,
        "deposit": 250000000,
        "specific_address": "Tầng 2, Tòa nhà A, Phân khu Căn Hộ Cao Cấp",
        "status": "empty",
        "description": "Căn hộ 2 phòng ngủ, tiện nghi và hiện đại.",
        "main_image" : "/customer/images/listing-1.jpg",
        "sub_image_1" : "/customer/images/image_2.jpg",
        "sub_image_2" : "/customer/images/image_4.jpg",
        "sub_image_3" : "/customer/images/image_6.jpg"
    },
    {
        "id": 8,
        "zone_id": 2,
        "name": "Lô căn hộ B1",
        "size": 85.0,
        "price": 1300000000,
        "deposit": 320000000,
        "specific_address": "Tầng 1, Tòa nhà B, Phân khu Căn Hộ Cao Cấp",
        "status": "empty",
        "description": "Căn hộ 3 phòng ngủ, view đẹp nhìn ra công viên.",
        "main_image" : "/customer/images/listing-3.jpg",
        "sub_image_1" : "/customer/images/image_5.jpg",
        "sub_image_2" : "/customer/images/image_1.jpg",
        "sub_image_3" : "/customer/images/image_8.jpg"
    },
    {
        "id": 9,
        "zone_id": 2,
        "name": "Lô căn hộ B2",
        "size": 70.0,
        "price": 1050000000,
        "deposit": 200000000,
        "specific_address": "Tầng 2, Tòa nhà B, Phân khu Căn Hộ Cao Cấp",
        "status": "empty",
        "description": "Căn hộ 2 phòng ngủ, gần khu vực tập gym.",
        "main_image" : "/customer/images/listing-5.jpg",
        "sub_image_1" : "/customer/images/image_4.jpg",
        "sub_image_2" : "/customer/images/image_5.jpg",
        "sub_image_3" : "/customer/images/image_6.jpg"
    },
    {
        "id": 10,
        "zone_id": 2,
        "name": "Lô căn hộ C1",
        "size": 90.0,
        "price": 1350000000,
        "deposit": 350000000,
        "specific_address": "Tầng 1, Tòa nhà C, Phân khu Căn Hộ Cao Cấp",
        "status": "empty",
        "description": "Căn hộ 3 phòng ngủ, thiết kế thông minh.",
        "main_image" : "/customer/images/listing-2.jpg",
        "sub_image_1" : "/customer/images/image_1.jpg",
        "sub_image_2" : "/customer/images/image_3.jpg",
        "sub_image_3" : "/customer/images/image_8.jpg"
    },
    {
        "id": 11,
        "zone_id": 3,
        "name": "Lô nhà phố TM-1",
        "size": 120.0,
        "price": 3000000000,
        "deposit": 600000000,
        "specific_address": "Khu TM-1, Phân khu Nhà Phố Thương Mại",
        "status": "empty",
        "description": "Lô nhà phố kinh doanh góc, thuận tiện giao thương.",
        "main_image" : "/customer/images/listing-1.jpg",
        "sub_image_1" : "/customer/images/image_1.jpg",
        "sub_image_2" : "/customer/images/image_2.jpg",
        "sub_image_3" : "/customer/images/image_3.jpg"
    },
    {
        "id": 12,
        "zone_id": 3,
        "name": "Lô nhà phố TM-2",
        "size": 100.0,
        "price": 2800000000,
        "deposit": 560000000,
        "specific_address": "Khu TM-2, Phân khu Nhà Phố Thương Mại",
        "status": "empty",
        "description": "Lô nhà phố nằm gần trung tâm tiện ích.",
        "main_image" : "/customer/images/listing-1.jpg",
        "sub_image_1" : "/customer/images/image_1.jpg",
        "sub_image_2" : "/customer/images/image_2.jpg",
        "sub_image_3" : "/customer/images/image_3.jpg"
    },
    {
        "id": 13,
        "zone_id": 3,
        "name": "Lô nhà phố TM-3",
        "size": 110.0,
        "price": 2900000000,
        "deposit": 580000000,
        "specific_address": "Khu TM-3, Phân khu Nhà Phố Thương Mại",
        "status": "empty",
        "description": "Lô nhà phố có thiết kế hiện đại, gần khu công viên.",
        "main_image" : "/customer/images/listing-1.jpg",
        "sub_image_1" : "/customer/images/image_1.jpg",
        "sub_image_2" : "/customer/images/image_2.jpg",
        "sub_image_3" : "/customer/images/image_3.jpg"
    },
    {
        "id": 14,
        "zone_id": 3,
        "name": "Lô nhà phố TM-4",
        "size": 130.0,
        "price": 3200000000,
        "deposit": 640000000,
        "specific_address": "Khu TM-4, Phân khu Nhà Phố Thương Mại",
        "status": "empty",
        "description": "Lô nhà phố 2 mặt tiền, thuận lợi cho kinh doanh.",
        "main_image" : "/customer/images/listing-1.jpg",
        "sub_image_1" : "/customer/images/image_1.jpg",
        "sub_image_2" : "/customer/images/image_2.jpg",
        "sub_image_3" : "/customer/images/image_3.jpg"
    },
    {
        "id": 15,
        "zone_id": 3,
        "name": "Lô nhà phố TM-5",
        "size": 115.0,
        "price": 2850000000,
        "deposit": 570000000,
        "specific_address": "Khu TM-5, Phân khu Nhà Phố Thương Mại",
        "status": "empty",
        "description": "Lô nhà phố gần khu vực vui chơi giải trí.",
        "main_image" : "/customer/images/listing-1.jpg",
        "sub_image_1" : "/customer/images/image_1.jpg",
        "sub_image_2" : "/customer/images/image_2.jpg",
        "sub_image_3" : "/customer/images/image_3.jpg"
    },
    {
        "id": 16,
        "zone_id": 4,
        "name": "Lô công viên CP-1",
        "size": 200.0,
        "price": 2500000000,
        "deposit": 500000000,
        "specific_address": "Khu CP-1, Phân khu Công Viên Trung Tâm",
        "status": "empty",
        "description": "Lô đất nằm gần hồ nước, cảnh quan thoáng mát.",
        "main_image" : "/customer/images/listing-1.jpg",
        "sub_image_1" : "/customer/images/image_1.jpg",
        "sub_image_2" : "/customer/images/image_2.jpg",
        "sub_image_3" : "/customer/images/image_3.jpg"
    },
    {
        "id": 17,
        "zone_id": 4,
        "name": "Lô công viên CP-2",
        "size": 180.0,
        "price": 2300000000,
        "deposit": 460000000,
        "specific_address": "Khu CP-2, Phân khu Công Viên Trung Tâm",
        "status": "empty",
        "description": "Lô đất gần khu vực cây xanh, không gian yên tĩnh.",
        "main_image" : "/customer/images/listing-1.jpg",
        "sub_image_1" : "/customer/images/image_1.jpg",
        "sub_image_2" : "/customer/images/image_2.jpg",
        "sub_image_3" : "/customer/images/image_3.jpg"
    },
    {
        "id": 18,
        "zone_id": 4,
        "name": "Lô công viên CP-3",
        "size": 210.0,
        "price": 2600000000,
        "deposit": 520000000,
        "specific_address": "Khu CP-3, Phân khu Công Viên Trung Tâm",
        "status": "empty",
        "description": "Lô đất gần khu vực thể thao, lý tưởng cho gia đình.",
        "main_image" : "/customer/images/listing-1.jpg",
        "sub_image_1" : "/customer/images/image_1.jpg",
        "sub_image_2" : "/customer/images/image_2.jpg",
        "sub_image_3" : "/customer/images/image_3.jpg"
    },
    {
        "id": 19,
        "zone_id": 4,
        "name": "Lô công viên CP-4",
        "size": 220.0,
        "price": 2700000000,
        "deposit": 540000000,
        "specific_address": "Khu CP-4, Phân khu Công Viên Trung Tâm",
        "status": "empty",
        "description": "Lô đất rộng, view hồ và công viên.",
        "main_image" : "/customer/images/listing-1.jpg",
        "sub_image_1" : "/customer/images/image_1.jpg",
        "sub_image_2" : "/customer/images/image_2.jpg",
        "sub_image_3" : "/customer/images/image_3.jpg"
    },
    {
        "id": 20,
        "zone_id": 4,
        "name": "Lô công viên CP-5",
        "size": 190.0,
        "price": 2400000000,
        "deposit": 480000000,
        "specific_address": "Khu CP-5, Phân khu Công Viên Trung Tâm",
        "status": "empty",
        "description": "Lô đất gần khu vực giải trí ngoài trời.",
        "main_image" : "/customer/images/listing-2.jpg",
        "sub_image_1" : "/customer/images/image_1.jpg",
        "sub_image_2" : "/customer/images/image_3.jpg",
        "sub_image_3" : "/customer/images/image_8.jpg"
    },
    {
        "id": 21,
        "zone_id": 5,
        "name": "Lô giải trí VC-1",
        "size": 150.0,
        "price": 2000000000,
        "deposit": 400000000,
        "specific_address": "Khu VC-1, Phân khu Khu Vui Chơi Giải Trí",
        "status": "empty",
        "description": "Lô đất gần khu thể thao, phù hợp cho các dịch vụ giải trí.",
        "main_image" : "/customer/images/listing-1.jpg",
        "sub_image_1" : "/customer/images/image_1.jpg",
        "sub_image_2" : "/customer/images/image_2.jpg",
        "sub_image_3" : "/customer/images/image_3.jpg"
    },
    {
        "id": 22,
        "zone_id": 5,
        "name": "Lô giải trí VC-2",
        "size": 170.0,
        "price": 2200000000,
        "deposit": 440000000,
        "specific_address": "Khu VC-2, Phân khu Khu Vui Chơi Giải Trí",
        "status": "empty",
        "description": "Lô đất nằm ở trung tâm khu vui chơi.",
        "main_image" : "/customer/images/listing-4.jpg",
        "sub_image_1" : "/customer/images/image_6.jpg",
        "sub_image_2" : "/customer/images/image_7.jpg",
        "sub_image_3" : "/customer/images/image_8.jpg"
    },
    {
        "id": 23,
        "zone_id": 5,
        "name": "Lô giải trí VC-3",
        "size": 160.0,
        "price": 2100000000,
        "deposit": 420000000,
        "specific_address": "Khu VC-3, Phân khu Khu Vui Chơi Giải Trí",
        "status": "empty",
        "description": "Lô đất gần khu vực tập gym và spa.",
        "main_image" : "/customer/images/listing-3.jpg",
        "sub_image_1" : "/customer/images/image_4.jpg",
        "sub_image_2" : "/customer/images/image_5.jpg",
        "sub_image_3" : "/customer/images/image_6.jpg"
    },
    {
        "id": 24,
        "zone_id": 5,
        "name": "Lô giải trí VC-4",
        "size": 180.0,
        "price": 2300000000,
        "deposit": 460000000,
        "specific_address": "Khu VC-4, Phân khu Khu Vui Chơi Giải Trí",
        "status": "empty",
        "description": "Lô đất gần khu vực giải trí ngoài trời.",
        "main_image" : "/customer/images/listing-2.jpg",
        "sub_image_1" : "/customer/images/image_3.jpg",
        "sub_image_2" : "/customer/images/image_4.jpg",
        "sub_image_3" : "/customer/images/image_5.jpg"
    },
    {
        "id": 25,
        "zone_id": 5,
        "name": "Lô giải trí VC-5",
        "size": 155.0,
        "price": 2050000000,
        "deposit": 410000000,
        "specific_address": "Khu VC-5, Phân khu Khu Vui Chơi Giải Trí",
        "status": "empty",
        "description": "Lô đất phù hợp cho các hoạt động vui chơi mạo hiểm.",
        "main_image" : "/customer/images/listing-1.jpg",
        "sub_image_1" : "/customer/images/image_1.jpg",
        "sub_image_2" : "/customer/images/image_2.jpg",
        "sub_image_3" : "/customer/images/image_3.jpg"
    }
]
